wowool/anonymizer/__init__.py
wowool/anonymizer/core/anonymizer.py
wowool/anonymizer/core/anonymizer_config.py
wowool/anonymizer/core/app_id.py
wowool/anonymizer/core/byte_writer.py
wowool/anonymizer/core/default_writer.py
wowool/anonymizer/core/defines.py
wowool/anonymizer/core/writer_interface.py
wowool/anonymizer/writers/factory/writer.py
wowool/anonymizer/writers/pdf/writer.py
wowool/anonymizer/writers/text/writer.py
wowool/apps/anonymizer/__init__.py
wowool/apps/anonymizer/config.py
wowool/tools/anonymizer/__main__.py
wowool/tools/anonymizer/writer_config.py
wowool/tools/pdf_anonymizer/__main__.py
wowool/tools/pdf_anonymizer/pdf_wow_anonymizer.json
wowool_anonymizer-2.1.1.dist-info/METADATA
wowool_anonymizer-2.1.1.dist-info/WHEEL
wowool_anonymizer-2.1.1.dist-info/entry_points.txt
wowool_anonymizer-2.1.1.dist-info/top_level.txt
wowool_anonymizer-2.1.1.dist-info/RECORD
