Metadata-Version: 2.4
Name: wowool-anonymizer
Version: 2.1.1
Summary: Wowool Anonymizer
Home-page: https://www.wowool.com/
Author: Wowool
Author-email: info@wowool.com
Requires-Python: >=3.10
Requires-Dist: Faker==36.1.0
Requires-Dist: jsonargparse
Dynamic: author
Dynamic: author-email
Dynamic: description
Dynamic: description-content-type
Dynamic: home-page
Dynamic: requires-dist
Dynamic: requires-python
Dynamic: summary
